{
  "tracks": [
    {
      "name": "Ai Đưa Em Về",
      "artist": "Tia",
      "image": "https://lastfm.freetls.fastly.net/i/u/174s/b591fc87d36d80bf34bc6d9fab085900.jpg",
      "nowPlaying": true,
      "timestamp": null
    },
    {
      "name": "Мой мармеладный (Я не права)",
      "artist": "Katya Lel",
      "image": "https://lastfm.freetls.fastly.net/i/u/174s/fd6f1e22a24e59eeed67f3ce108861e0.jpg",
      "nowPlaying": false,
      "timestamp": 1772770923
    },
    {
      "name": "КЛЕТКА",
      "artist": "Quest Pistols",
      "image": "https://lastfm.freetls.fastly.net/i/u/174s/e195c86a2aa14b7facadc4289288af23.png",
      "nowPlaying": false,
      "timestamp": 1772728142
    },
    {
      "name": "Circus",
      "artist": "Britney Spears",
      "image": "https://lastfm.freetls.fastly.net/i/u/174s/9d297c35bd0a5feb9f9b697d9b96bf07.png",
      "nowPlaying": false,
      "timestamp": 1772727950
    },
    {
      "name": "Girlfriend",
      "artist": "Avril Lavigne",
      "image": "https://lastfm.freetls.fastly.net/i/u/174s/325277ba46fb77d5a1d1f65ec7df5b75.jpg",
      "nowPlaying": false,
      "timestamp": 1772727732
    }
  ]
}